dtstools/__init__.py
dtstools/dtsTable.py
dtstools-0.0.9.dist-info/LICENSE
dtstools-0.0.9.dist-info/METADATA
dtstools-0.0.9.dist-info/WHEEL
dtstools-0.0.9.dist-info/top_level.txt
dtstools-0.0.9.dist-info/RECORD
