Metadata-Version: 2.1
Name: dtstools
Version: 0.0.9
Summary: This package aims to provide features for working with Delta Lake.
Author-email: Reginaldo Silva <reginaldo.silva@dataside.com.br>
License: MIT License
Project-URL: DataInAction, https://www.datainaction.dev/blog
Project-URL: Bug Tracker, https://github.com/reginaldosilva27/dtstools
Project-URL: README, https://www.datainaction.dev/blog
Project-URL: Dataside, https://www.dataside.com.br
Keywords: tableSize,tableMaintenance,help,deltaLake,Spark,Databricks,Fabric
Classifier: Programming Language :: Python :: 3
Classifier: License :: OSI Approved :: MIT License
Classifier: Operating System :: OS Independent
Requires-Python: >=3.7
License-File: LICENSE
